{
    "id": "2cbbd7cf8c176183e50ffd52a432b866",
    "name": "System Award Management API",
    "description": null,
    "auth": null,
    "events": null,
    "variables": [],
    "order": [],
    "folders_order": [],
    "folders": [],
    "requests": [
        {
            "id": "d1d398380862b266ff0614046bd6c94a",
            "name": "Find a registration by its DUN+4 number",
            "url": "httpsapi.data.gov\/sam\/v1\/registrations\/{registrationId}",
            "description": "If the entity only has a 9-digit DUNS number, pad the end to include 4 zeros",
            "data": [],
            "dataMode": "raw",
            "headerData": null,
            "method": "GET",
            "pathVariableData": [],
            "queryParams": [
                {
                    "key": "registrationId",
                    "description": "DUNS+4 number (no '-' sign) of the registration to be fetched",
                    "value": "",
                    "equals": true,
                    "enabled": true
                },
                {
                    "key": "api_key",
                    "description": "An API Key from api.data.gov",
                    "value": "",
                    "equals": true,
                    "enabled": true
                }
            ],
            "auth": null,
            "events": null,
            "folder": null,
            "protocolProfileBehavior": {
                "disableBodyPruning": true
            },
            "responses": [],
            "currentHelper": null,
            "helperAttributes": null,
            "collectionId": "2cbbd7cf8c176183e50ffd52a432b866",
            "rawModeData": ""
        }
    ]
}